README.txt
setup.py
walklog
walklog/__init__.py
walklog/_better_exceptions.py
walklog/_colorama.py
walklog/_colored_string.py
walklog/_ctime_functions.py
walklog/_datetime.py
walklog/_defaults.py
walklog/_file_sink.py
walklog/_filters.py
walklog/_get_frame.py
walklog/_handler.py
walklog/_logger.py
walklog/_my_logger.py
walklog/_recattrs.py
walklog/_simple_sinks.py
walklog/_string_parsers.py
walklog.egg-info/PKG-INFO
walklog.egg-info/SOURCES.txt
walklog.egg-info/dependency_links.txt
walklog.egg-info/top_level.txt