Metadata-Version: 2.1
Name: walklog
Version: 0.1
Summary: My own customized Loguru
Home-page: https://github.com/javatechy/dokr
Author: Priyansh Tiwari
Author-email: Priyansh.tiwari99@gmail.com
License: UNKNOWN
Platform: UNKNOWN
Classifier: Programming Language :: Python :: 3
Classifier: License :: OSI Approved :: MIT License
Classifier: Operating System :: OS Independent
